BanglaFastText/__init__.py
BanglaFastText-2.3.dist-info/METADATA
BanglaFastText-2.3.dist-info/WHEEL
BanglaFastText-2.3.dist-info/top_level.txt
BanglaFastText-2.3.dist-info/RECORD
