Metadata-Version: 2.1
Name: BanglaFastText
Version: 2.3
Summary: UNKNOWN
Home-page: https://github.com/Kowsher/Bangla-Fasttext
Author: Kowsher, Md. Shohanur Islam Sobuj, Md. Fahim Shahriar
Author-email: ga.kowsher@gmail.com, shohanursobuj@gmail.com, fahimshahriar6832@gmail.com
License: MIT
Platform: UNKNOWN
Classifier: Programming Language :: Python :: 3
Classifier: License :: OSI Approved :: MIT License
Classifier: Operating System :: OS Independent
Requires-Dist: gdown
Requires-Dist: gensim (==4.0.1)
Requires-Dist: numpy
Requires-Dist: tqdm
